.coveragerc
.travis.yml
AUTHORS
ChangeLog
README.rst
dev-requirements.txt
requirements.txt
setup.cfg
setup.py
tasks.py
test_zero_buffer.py
tox.ini
zero_buffer.py
.travis/install.sh
bench/bench_line_reading.py
docs/Makefile
docs/api-reference.rst
docs/conf.py
docs/index.rst
docs/make.bat
docs/_static/.keepme
zero_buffer.egg-info/PKG-INFO
zero_buffer.egg-info/SOURCES.txt
zero_buffer.egg-info/dependency_links.txt
zero_buffer.egg-info/not-zip-safe
zero_buffer.egg-info/requires.txt
zero_buffer.egg-info/top_level.txt