Metadata-Version: 1.0
Name: zero-buffer
Version: 0.5.1
Summary: A fast, no-copy, buffer for Python
Home-page: https://github.com/alex/zero_buffer
Author: Alex Gaynor and David Reid
Author-email: alex.gaynor@gmail.com
License: BSD
Platform: UNKNOWN
